twisted/plugins/serviceplugin.py
txwerewolves/__init__.py
txwerewolves/apps.py
txwerewolves/auth.py
txwerewolves/compat.py
txwerewolves/dialogs.py
txwerewolves/game.py
txwerewolves/graphics_chars.py
txwerewolves/interfaces.py
txwerewolves/lobby.py
txwerewolves/service.py
txwerewolves/session.py
txwerewolves/term.py
txwerewolves/todo.py
txwerewolves/users.py
txwerewolves/utils.py
txwerewolves/webauth.py
txwerewolves/webservice.py
txwerewolves/werewolf.py
txwerewolves/html/lobby.html
txwerewolves/html/login.html
txwerewolves/html/werewolves.html
txwerewolves/static/bootstrap-4.0.0-dist/css/bootstrap-grid.css
txwerewolves/static/bootstrap-4.0.0-dist/css/bootstrap-grid.css.map
txwerewolves/static/bootstrap-4.0.0-dist/css/bootstrap-grid.min.css
txwerewolves/static/bootstrap-4.0.0-dist/css/bootstrap-grid.min.css.map
txwerewolves/static/bootstrap-4.0.0-dist/css/bootstrap-reboot.css
txwerewolves/static/bootstrap-4.0.0-dist/css/bootstrap-reboot.css.map
txwerewolves/static/bootstrap-4.0.0-dist/css/bootstrap-reboot.min.css
txwerewolves/static/bootstrap-4.0.0-dist/css/bootstrap-reboot.min.css.map
txwerewolves/static/bootstrap-4.0.0-dist/css/bootstrap.css
txwerewolves/static/bootstrap-4.0.0-dist/css/bootstrap.css.map
txwerewolves/static/bootstrap-4.0.0-dist/css/bootstrap.min.css
txwerewolves/static/bootstrap-4.0.0-dist/css/bootstrap.min.css.map
txwerewolves/static/bootstrap-4.0.0-dist/js/bootstrap.bundle.js
txwerewolves/static/bootstrap-4.0.0-dist/js/bootstrap.bundle.js.map
txwerewolves/static/bootstrap-4.0.0-dist/js/bootstrap.bundle.min.js
txwerewolves/static/bootstrap-4.0.0-dist/js/bootstrap.bundle.min.js.map
txwerewolves/static/bootstrap-4.0.0-dist/js/bootstrap.js
txwerewolves/static/bootstrap-4.0.0-dist/js/bootstrap.js.map
txwerewolves/static/bootstrap-4.0.0-dist/js/bootstrap.min.js
txwerewolves/static/bootstrap-4.0.0-dist/js/bootstrap.min.js.map
txwerewolves/static/css/styles.css
txwerewolves/static/js/jquery-3.3.1.min.js
txwerewolves/static/js/lobby.js
txwerewolves-0.6.3.dist-info/LICENSE.txt
txwerewolves-0.6.3.dist-info/METADATA
txwerewolves-0.6.3.dist-info/WHEEL
txwerewolves-0.6.3.dist-info/top_level.txt
txwerewolves-0.6.3.dist-info/RECORD
