Metadata-Version: 2.1
Name: txwerewolves
Version: 0.6.3
Summary: Networked adaption of the Werewolves party game for 3-10 players.
Home-page: https://github.com/cwaldbieser/txwerewolves
Author: Carl Waldbieser
Author-email: cwaldbieser@gmail.com
License: UNKNOWN
Project-URL: Bug Reports, https://github.com/cwaldbieser/txwerewolves/issues
Project-URL: Source, https://github.com/cwaldbieser/txwerewolves
Keywords: game multi-player network
Platform: UNKNOWN
Classifier: Development Status :: 3 - Alpha
Classifier: Topic :: Games/Entertainment :: Board Games
Classifier: License :: OSI Approved :: GNU General Public License v3 (GPLv3)
Classifier: Programming Language :: Python :: 2
Classifier: Programming Language :: Python :: 2.7
Classifier: Programming Language :: Python :: 3
Classifier: Programming Language :: Python :: 3.4
Classifier: Programming Language :: Python :: 3.5
Classifier: Programming Language :: Python :: 3.6
Requires-Python: >=2.7, !=3.0.*, !=3.1.*, !=3.2.*, <4
Requires-Dist: Automat (<1,>=0.6)
Requires-Dist: six (<2,>=1.11)
Requires-Dist: Twisted (>=19.7.0)
Requires-Dist: cryptography (<3,>=2.1.1)
Requires-Dist: pyasn1 (<1,>=0.3.7)
Requires-Dist: klein (<18,>=17.10)
Requires-Dist: bcrypt
